Metadata-Version: 2.1
Name: jsonnote
Version: 0.13
Summary: A simple utility for working with JSON files.
Home-page: UNKNOWN
Author: vipervit
Author-email: vitolg1@gmail.com
License: Apache
Platform: UNKNOWN
Classifier: Programming Language :: Python :: 3
Classifier: Intended Audience :: Developers
Classifier: Topic :: Utilities
